nested_chat_plugin_sdk/__init__.py
nested_chat_plugin_sdk/schemes.py
nested_chat_plugin_sdk/sdk.py
nested_chat_plugin_sdk-0.1.7.dist-info/LICENSE
nested_chat_plugin_sdk-0.1.7.dist-info/WHEEL
nested_chat_plugin_sdk-0.1.7.dist-info/METADATA
nested_chat_plugin_sdk-0.1.7.dist-info/RECORD
