Metadata-Version: 2.1
Name: nested-chat-plugin-sdk
Version: 0.1.7
Summary: Test
Author: vladvavilov
Author-email: vladvav94@gmail.com
Requires-Python: >=3.10,<4.0
Classifier: Programming Language :: Python :: 3
Classifier: Programming Language :: Python :: 3.10
Classifier: Programming Language :: Python :: 3.11
Requires-Dist: aiohttp (>=3.9.3,<4.0.0)
Requires-Dist: fastapi (>=0.103.0,<0.104.0)
Requires-Dist: pydantic-settings (>=2.0.3,<3.0.0)
